bavisitter/Bavisitter.py
bavisitter/__init__.py
bavisitter/model/__init__.py
bavisitter/model/ipc_model.py
bavisitter/model/message_model.py
bavisitter/static/main.js
bavisitter/tests/__init__.py
bavisitter/tests/test_Bavisitter.py
bavisitter/utils/__init__.py
bavisitter/utils/deep_equal.py
bavisitter/utils/file_browser.py
bavisitter/utils/get_chunk_type.py
bavisitter/utils/set_interpreter.py
bavisitter/utils/system_prompt.py
bavisitter-0.0.4.dist-info/METADATA
bavisitter-0.0.4.dist-info/WHEEL
bavisitter-0.0.4.dist-info/RECORD
