Metadata-Version: 2.3
Name: bavisitter
Version: 0.0.4
Requires-Dist: anywidget
Requires-Dist: open-interpreter
Requires-Dist: open-interpreter[safe]
Requires-Dist: openai
Requires-Dist: pandas
Provides-Extra: dev
Requires-Dist: jupyterlab; extra == 'dev'
Requires-Dist: pyright; extra == 'dev'
Requires-Dist: pytest; extra == 'dev'
Requires-Dist: pytest-cov; extra == 'dev'
Requires-Dist: ruff; extra == 'dev'
Requires-Dist: vega-datasets; extra == 'dev'
Requires-Dist: watchfiles; extra == 'dev'
